htimeseries/__init__.py
htimeseries/htimeseries.py
htimeseries/timezone_utils.py
htimeseries-8.0.0.dist-info/LICENSE
htimeseries-8.0.0.dist-info/METADATA
htimeseries-8.0.0.dist-info/WHEEL
htimeseries-8.0.0.dist-info/top_level.txt
htimeseries-8.0.0.dist-info/RECORD
