Metadata-Version: 2.1
Name: htimeseries
Version: 8.0.0
Summary: Hydrological and meteorological time series
Author-email: Antonis Christofides <antonis@antonischristofides.com>
Maintainer-email: Antonis Christofides <antonis@antonischristofides.com>
Project-URL: Homepage, https://github.com/openmeteo/htimeseries
Project-URL: Documentation, https://github.com/openmeteo/htimeseries
Project-URL: Repository, https://github.com/openmeteo/htimeseries
Project-URL: Issues, https://github.com/openmeteo/htimeseries/issues
Project-URL: Changelog, https://github.com/openmeteo/htimeseries/blob/master/HISTORY.rst
Keywords: time series
Classifier: Development Status :: 5 - Production/Stable
Classifier: Intended Audience :: Developers
Classifier: License :: OSI Approved :: GNU General Public License v3 (GPLv3)
Classifier: Natural Language :: English
Classifier: Programming Language :: Python :: 3.10
Classifier: Programming Language :: Python :: 3.11
Classifier: Programming Language :: Python :: 3.12
Classifier: Programming Language :: Python :: 3.13
Requires-Python: >=3.10
License-File: LICENSE
Requires-Dist: pandas<3,>=2.2
Requires-Dist: iso8601
Requires-Dist: textbisect
Requires-Dist: tzdata
